{
  "main": {
    "id": "ff4c868669b63a17",
    "type": "split",
    "children": [
      {
        "id": "743fe976baf947ac",
        "type": "tabs",
        "children": [
          {
            "id": "f3209c1b3b112d3b",
            "type": "leaf",
            "state": {
              "type": "markdown",
              "state": {
                "file": "Cloud Practitioner (CLF-C02)/Foundations on Cloud Computing/Module 2 - Compute in the Cloud/04A-Amazon Elastic Compute Cloud(EC2).md",
                "mode": "source",
                "source": false
              }
            }
          }
        ]
      }
    ],
    "direction": "vertical"
  },
  "left": {
    "id": "c4ea1c8dc8dd091a",
    "type": "split",
    "children": [
      {
        "id": "4393a55bbeb59fb9",
        "type": "tabs",
        "children": [
          {
            "id": "73d4ed226f12a917",
            "type": "leaf",
            "state": {
              "type": "file-explorer",
              "state": {
                "sortOrder": "alphabetical"
              }
            }
          },
          {
            "id": "6df3ff25b353af37",
            "type": "leaf",
            "state": {
              "type": "search",
              "state": {
                "query": "",
                "matchingCase": false,
                "explainSearch": false,
                "collapseAll": false,
                "extraContext": false,
                "sortOrder": "alphabetical"
              }
            }
          },
          {
            "id": "8bd0c3ba686146e8",
            "type": "leaf",
            "state": {
              "type": "bookmarks",
              "state": {}
            }
          }
        ]
      }
    ],
    "direction": "horizontal",
    "width": 300
  },
  "right": {
    "id": "f13950effe2ea861",
    "type": "split",
    "children": [
      {
        "id": "4897bb45cf3a14f8",
        "type": "tabs",
        "children": [
          {
            "id": "d83c7bdf241b7187",
            "type": "leaf",
            "state": {
              "type": "backlink",
              "state": {
                "file": "Cloud Practitioner (CLF-C02)/Foundations on Cloud Computing/Module 2 - Compute in the Cloud/04A-Amazon Elastic Compute Cloud(EC2).md",
                "collapseAll": false,
                "extraContext": false,
                "sortOrder": "alphabetical",
                "showSearch": false,
                "searchQuery": "",
                "backlinkCollapsed": false,
                "unlinkedCollapsed": true
              }
            }
          },
          {
            "id": "8719ea331e836d3a",
            "type": "leaf",
            "state": {
              "type": "outgoing-link",
              "state": {
                "file": "Cloud Practitioner (CLF-C02)/Foundations on Cloud Computing/Module 2 - Compute in the Cloud/04A-Amazon Elastic Compute Cloud(EC2).md",
                "linksCollapsed": false,
                "unlinkedCollapsed": true
              }
            }
          },
          {
            "id": "0e09d26ce8296526",
            "type": "leaf",
            "state": {
              "type": "tag",
              "state": {
                "sortOrder": "frequency",
                "useHierarchy": true
              }
            }
          },
          {
            "id": "ecd08ac0bb43b600",
            "type": "leaf",
            "state": {
              "type": "outline",
              "state": {
                "file": "Cloud Practitioner (CLF-C02)/Foundations on Cloud Computing/Module 2 - Compute in the Cloud/04A-Amazon Elastic Compute Cloud(EC2).md"
              }
            }
          }
        ]
      }
    ],
    "direction": "horizontal",
    "width": 300,
    "collapsed": true
  },
  "left-ribbon": {
    "hiddenItems": {
      "switcher:Open quick switcher": false,
      "graph:Open graph view": false,
      "canvas:Create new canvas": false,
      "daily-notes:Open today's daily note": false,
      "templates:Insert template": false,
      "command-palette:Open command palette": false
    }
  },
  "active": "f3209c1b3b112d3b",
  "lastOpenFiles": [
    "Cloud Practitioner (CLF-C02)/Foundations on Cloud Computing/Module 2 - Compute in the Cloud/04A-Amazon Elastic Compute Cloud(EC2).md",
    "Cloud Practitioner (CLF-C02)/Foundations on Cloud Computing/Foundations on Cloud Computing.md",
    "Cloud Practitioner (CLF-C02)/Foundations on Cloud Computing/Module 2 - Compute in the Cloud/05-Elastic Load Balancing(ELB).md",
    "Cloud Practitioner (CLF-C02)/Foundations on Cloud Computing/Module 2 - Compute in the Cloud/Module 2 - Compute in the Cloud.md",
    "Cloud Practitioner (CLF-C02)/Foundations on Cloud Computing/Module 2 - Compute in the Cloud/04D-Scalability.md",
    "Cloud Practitioner (CLF-C02)/Foundations on Cloud Computing/Module 2 - Compute in the Cloud/04C-Amazon EC2 Pricing.md",
    "Cloud Practitioner (CLF-C02)/Foundations on Cloud Computing/Module 2 - Compute in the Cloud/04B-Amazon EC2 instance types.md",
    "Cloud Practitioner (CLF-C02)/Foundations on Cloud Computing/Module 2 - Compute in the Cloud/03-Client-Server Model.md",
    "Cloud Practitioner (CLF-C02)/Foundations on Cloud Computing/Module 2 - Compute in the Cloud",
    "Cloud Practitioner (CLF-C02)/Foundations on Cloud Computing/Module 1 - Introduction to AWS/Module 1 - Introduction to AWS.md",
    "Cloud Practitioner (CLF-C02)/Foundations on Cloud Computing/Module 1 - Introduction to AWS/02-Cloud Deployment Models.md",
    "Cloud Practitioner (CLF-C02)/Foundations on Cloud Computing/Module 1 - Introduction to AWS/01B-Advantages of Cloud Computing.md",
    "Cloud Practitioner (CLF-C02)/Foundations on Cloud Computing/Module 1 - Introduction to AWS/01A-Cloud Computing.md",
    "Cloud Practitioner (CLF-C02)/Foundations on Cloud Computing/Module 1 - Introduction to AWS",
    "Cloud Practitioner (CLF-C02)/Foundations on Cloud Computing/41-The AWS Well-Architected Framework.md",
    "Cloud Practitioner (CLF-C02)/Foundations on Cloud Computing/39-AWS Snow Family.md",
    "Cloud Practitioner (CLF-C02)/Foundations on Cloud Computing/img/the_aws_well_structured_framework.png",
    "Cloud Practitioner (CLF-C02)/Foundations on Cloud Computing/40-Innovate with AWS Services.md",
    "Cloud Practitioner (CLF-C02)/Foundations on Cloud Computing/37-AWS Cloud Adoption Framework.md",
    "Cloud Practitioner (CLF-C02)/Foundations on Cloud Computing/img/amazon_q_developer.png",
    "Cloud Practitioner (CLF-C02)/Foundations on Cloud Computing/img/aws_snow_family.png",
    "Cloud Practitioner (CLF-C02)/Foundations on Cloud Computing/38-Migration Strategies.md",
    "Cloud Practitioner (CLF-C02)/Foundations on Cloud Computing/08A-AWS Global Infrastructure.md",
    "Cloud Practitioner (CLF-C02)/Foundations on Cloud Computing/36-AWS Marketplace.md",
    "Cloud Practitioner (CLF-C02)/Foundations on Cloud Computing/33-AWS Budgets.md",
    "Cloud Practitioner (CLF-C02)/Foundations on Cloud Computing/32-Consolidated Billing.md",
    "Cloud Practitioner (CLF-C02)/Foundations on Cloud Computing/35-AWS Support.md",
    "Cloud Practitioner (CLF-C02)/Foundations on Cloud Computing/34-AWS Cost Explorer.md",
    "Cloud Practitioner (CLF-C02)/Foundations on Cloud Computing/img/aws_marketplace_categories.png",
    "Pasted image 20240808104507.png",
    "Cloud Practitioner (CLF-C02)/Foundations on Cloud Computing/img/aws_cost_explorer_example.png",
    "Cloud Practitioner (CLF-C02)/Foundations on Cloud Computing/img/aws_budgets_example.png",
    "Cloud Practitioner (CLF-C02)/Foundations on Cloud Computing/img/consolidated_billing3.png",
    "Cloud Practitioner (CLF-C02)/Foundations on Cloud Computing/img/consolidated_billing2.png",
    "Cloud Practitioner (CLF-C02)/Foundations on Cloud Computing/img/consolidated_billing1.png",
    "Cloud Practitioner (CLF-C02)/Foundations on Cloud Computing/31-Pricing.md",
    "Cloud Practitioner (CLF-C02)/Foundations on Cloud Computing/30-AWS Free Tier.md",
    "Cloud Practitioner (CLF-C02)/Foundations on Cloud Computing/26-Additional Security Services.md",
    "Cloud Practitioner (CLF-C02)",
    "Foundations on Cloud Computing/Untitled",
    "Cloud Practitioner (CLF-C02)/Foundations on Cloud Computing/img",
    "Cloud Practitioner (CLF-C02)/Foundations on Cloud Computing"
  ]
}